[
    {
      "ROUND": 3,
      "MONKEY": "SUBMARINE_1",
      "UPGRADE": null,
      "UPGRADE_DIFF": null,
      "TARGET": null,
      "TARGET_POS": null,
      "POSITION": "1454, 578",
      "KEYCODE": "x",
      "ROUND_START": "FALSE"
    },
    {
      "ROUND": 3,
      "MONKEY": "DART_1",
      "UPGRADE": null,
      "UPGRADE_DIFF": null,
      "TARGET": "LAST, STRONG",
      "TARGET_POS": null,
      "POSITION": "773, 658",
      "KEYCODE": "q",
      "ROUND_START": "TRUE"
    },
    {
      "ROUND": 4,
      "MONKEY": "DART_2",
      "UPGRADE": null,
      "UPGRADE_DIFF": null,
      "TARGET": "STRONG",
      "TARGET_POS": null,
      "POSITION": "785, 814",
      "KEYCODE": "q",
      "ROUND_START": "FALSE"
    },
    {
      "ROUND": 9,
      "MONKEY": "SUBMARINE_2",
      "UPGRADE": null,
      "UPGRADE_DIFF": null,
      "TARGET": null,
      "TARGET_POS": null,
      "POSITION": "1452, 922",
      "KEYCODE": "x",
      "ROUND_START": "FALSE"
    },
    {
      "ROUND": 12,
      "MONKEY": "OBYN",
      "UPGRADE": null,
      "UPGRADE_DIFF": null,
      "TARGET": null,
      "TARGET_POS": null,
      "POSITION": "1345, 598",
      "KEYCODE": "u",
      "ROUND_START": "FALSE"
    },
    {
      "ROUND": 14,
      "MONKEY": "SUBMARINE_2",
      "UPGRADE": "0-0-1",
      "UPGRADE_DIFF": "0-0-1",
      "TARGET": null,
      "TARGET_POS": null,
      "POSITION": "1452, 922",
      "KEYCODE": "x",
      "ROUND_START": "FALSE"
    },
    {
      "ROUND": 15,
      "MONKEY": "SUBMARINE_2",
      "UPGRADE": "1-0-1",
      "UPGRADE_DIFF": "1-0-0",
      "TARGET": null,
      "TARGET_POS": null,
      "POSITION": "1452, 922",
      "KEYCODE": "x",
      "ROUND_START": "FALSE"
    },
    {
      "ROUND": 17,
      "MONKEY": "SUBMARINE_2",
      "UPGRADE": "2-0-1",
      "UPGRADE_DIFF": "1-0-0",
      "TARGET": null,
      "TARGET_POS": null,
      "POSITION": "1452, 922",
      "KEYCODE": "x",
      "ROUND_START": "FALSE"
    },
    {
      "ROUND": 21,
      "MONKEY": "SUBMARINE_2",
      "UPGRADE": "2-0-2",
      "UPGRADE_DIFF": "0-0-1",
      "TARGET": null,
      "TARGET_POS": null,
      "POSITION": "1452, 922",
      "KEYCODE": "x",
      "ROUND_START": "FALSE"
    },
    {
      "ROUND": 22,
      "MONKEY": "DART_1",
      "UPGRADE": "0-0-2",
      "UPGRADE_DIFF": "0-0-2",
      "TARGET": null,
      "TARGET_POS": null,
      "POSITION": "773, 658",
      "KEYCODE": "q",
      "ROUND_START": "FALSE"
    },
    {
      "ROUND": 24,
      "MONKEY": "ALCH_1",
      "UPGRADE": null,
      "UPGRADE_DIFF": null,
      "TARGET": "STRONG",
      "TARGET_POS": null,
      "POSITION": "1353, 901",
      "KEYCODE": "f",
      "ROUND_START": "FALSE"
    },
    {
      "ROUND": 28,
      "MONKEY": "SUBMARINE_2",
      "UPGRADE": "2-0-3",
      "UPGRADE_DIFF": "0-0-1",
      "TARGET": null,
      "TARGET_POS": null,
      "POSITION": "1452, 922",
      "KEYCODE": "x",
      "ROUND_START": "FALSE"
    },
    {
      "ROUND": 29,
      "MONKEY": "ALCH_1",
      "UPGRADE": "2-0-0",
      "UPGRADE_DIFF": "2-0-0",
      "TARGET": null,
      "TARGET_POS": null,
      "POSITION": "1353, 901",
      "KEYCODE": "f",
      "ROUND_START": "FALSE"
    },
    {
      "ROUND": 33,
      "MONKEY": "ALCH_1",
      "UPGRADE": "3-0-0",
      "UPGRADE_DIFF": "1-0-0",
      "TARGET": null,
      "TARGET_POS": null,
      "POSITION": "1353, 901",
      "KEYCODE": "f",
      "ROUND_START": "FALSE"
    },
    {
      "ROUND": 35,
      "MONKEY": "SUBMARINE_1",
      "UPGRADE": "2-0-1",
      "UPGRADE_DIFF": "2-0-1",
      "TARGET": null,
      "TARGET_POS": null,
      "POSITION": "1454, 578",
      "KEYCODE": "x",
      "ROUND_START": "FALSE"
    },
    {
      "ROUND": 36,
      "MONKEY": "SUBMARINE_1",
      "UPGRADE": "2-0-2",
      "UPGRADE_DIFF": "0-0-1",
      "TARGET": null,
      "TARGET_POS": null,
      "POSITION": "1454, 578",
      "KEYCODE": "x",
      "ROUND_START": "FALSE"
    },
    {
      "ROUND": 38,
      "MONKEY": "SUBMARINE_1",
      "UPGRADE": "2-0-3",
      "UPGRADE_DIFF": "0-0-1",
      "TARGET": null,
      "TARGET_POS": null,
      "POSITION": "1454, 578",
      "KEYCODE": "x",
      "ROUND_START": "FALSE"
    },
    {
      "ROUND": 39,
      "MONKEY": "SUPER_1",
      "UPGRADE": null,
      "UPGRADE_DIFF": null,
      "TARGET": null,
      "TARGET_POS": null,
      "POSITION": "1216, 579",
      "KEYCODE": "s",
      "ROUND_START": "FALSE"
    },
    {
      "ROUND": 41,
      "MONKEY": "VILLAGE_1",
      "UPGRADE": null,
      "UPGRADE_DIFF": null,
      "TARGET": null,
      "TARGET_POS": null,
      "POSITION": "1144, 358",
      "KEYCODE": "k",
      "ROUND_START": "FALSE"
    },
    {
      "ROUND": 41,
      "MONKEY": "VILLAGE_1",
      "UPGRADE": "0-0-2",
      "UPGRADE_DIFF": "0-0-2",
      "TARGET": null,
      "TARGET_POS": null,
      "POSITION": "1144, 358",
      "KEYCODE": "k",
      "ROUND_START": "FALSE"
    },
    {
      "ROUND": 42,
      "MONKEY": "VILLAGE_2",
      "UPGRADE": null,
      "UPGRADE_DIFF": null,
      "TARGET": null,
      "TARGET_POS": null,
      "POSITION": "1007, 430",
      "KEYCODE": "k",
      "ROUND_START": "FALSE"
    },
    {
      "ROUND": 42,
      "MONKEY": "VILLAGE_2",
      "UPGRADE": "0-0-2",
      "UPGRADE_DIFF": "0-0-2",
      "TARGET": null,
      "TARGET_POS": null,
      "POSITION": "1007, 430",
      "KEYCODE": "k",
      "ROUND_START": "FALSE"
    },
    {
      "ROUND": 45,
      "MONKEY": "SUPER_1",
      "UPGRADE": "0-0-1",
      "UPGRADE_DIFF": "0-0-1",
      "TARGET": null,
      "TARGET_POS": null,
      "POSITION": "1216, 579",
      "KEYCODE": "s",
      "ROUND_START": "FALSE"
    },
    {
      "ROUND": 46,
      "MONKEY": "SUPER_1",
      "UPGRADE": "0-0-2",
      "UPGRADE_DIFF": "0-0-1",
      "TARGET": null,
      "TARGET_POS": null,
      "POSITION": "1216, 579",
      "KEYCODE": "s",
      "ROUND_START": "FALSE"
    },
    {
      "ROUND": 47,
      "MONKEY": "SUPER_1",
      "UPGRADE": "1-0-2",
      "UPGRADE_DIFF": "1-0-0",
      "TARGET": null,
      "TARGET_POS": null,
      "POSITION": "1216, 579",
      "KEYCODE": "s",
      "ROUND_START": "FALSE"
    },
    {
      "ROUND": 49,
      "MONKEY": "SUPER_1",
      "UPGRADE": "2-0-2",
      "UPGRADE_DIFF": "1-0-0",
      "TARGET": null,
      "TARGET_POS": null,
      "POSITION": "1216, 579",
      "KEYCODE": "s",
      "ROUND_START": "FALSE"
    },
    {
      "ROUND": 49,
      "MONKEY": "ALCH_2",
      "UPGRADE": null,
      "UPGRADE_DIFF": null,
      "TARGET": null,
      "TARGET_POS": null,
      "POSITION": "1154, 468",
      "KEYCODE": "f",
      "ROUND_START": "FALSE"
    },
    {
      "ROUND": 50,
      "MONKEY": "ALCH_2",
      "UPGRADE": "4-2-0",
      "UPGRADE_DIFF": "4-2-0",
      "TARGET": null,
      "TARGET_POS": null,
      "POSITION": "1154, 468",
      "KEYCODE": "f",
      "ROUND_START": "FALSE"
    },
    {
      "ROUND": 50,
      "MONKEY": "VILLAGE_1",
      "UPGRADE": "2-0-2",
      "UPGRADE_DIFF": "2-0-0",
      "TARGET": null,
      "TARGET_POS": null,
      "POSITION": "1144, 358",
      "KEYCODE": "k",
      "ROUND_START": "FALSE"
    },
    {
      "ROUND": 61,
      "MONKEY": "SUPER_1",
      "UPGRADE": "3-0-2",
      "UPGRADE_DIFF": "1-0-0",
      "TARGET": null,
      "TARGET_POS": null,
      "POSITION": "1216, 579",
      "KEYCODE": "s",
      "ROUND_START": "FALSE"
    },
    {
      "ROUND": 62,
      "MONKEY": "SPIKE_1",
      "UPGRADE": null,
      "UPGRADE_DIFF": null,
      "TARGET": null,
      "TARGET_POS": null,
      "POSITION": "2027, 684",
      "KEYCODE": "j",
      "ROUND_START": "FALSE"
    },
    {
      "ROUND": 63,
      "MONKEY": "SPIKE_1",
      "UPGRADE": "0-0-3",
      "UPGRADE_DIFF": "0-0-3",
      "TARGET": "CLOSE",
      "TARGET_POS": null,
      "POSITION": "2027, 684",
      "KEYCODE": "j",
      "ROUND_START": "FALSE"
    },
    {
      "ROUND": 65,
      "MONKEY": "SPIKE_1",
      "UPGRADE": "0-0-4",
      "UPGRADE_DIFF": "0-0-1",
      "TARGET": null,
      "TARGET_POS": null,
      "POSITION": "2027, 684",
      "KEYCODE": "j",
      "ROUND_START": "FALSE"
    },
    {
      "ROUND": 80,
      "MONKEY": "SPIKE_1",
      "UPGRADE": "0-0-5",
      "UPGRADE_DIFF": "0-0-1",
      "TARGET": null,
      "TARGET_POS": null,
      "POSITION": "2027, 684",
      "KEYCODE": "j",
      "ROUND_START": "FALSE"
    },
    {
      "ROUND": 80,
      "MONKEY": "SPIKE_1",
      "UPGRADE": "2000-02-05",
      "UPGRADE_DIFF": "0-2-0",
      "TARGET": null,
      "TARGET_POS": null,
      "POSITION": "2027, 684",
      "KEYCODE": "j",
      "ROUND_START": "FALSE"
    },
    {
      "ROUND": 82,
      "MONKEY": "VILLAGE_3",
      "UPGRADE": null,
      "UPGRADE_DIFF": null,
      "TARGET": null,
      "TARGET_POS": null,
      "POSITION": "2078, 570",
      "KEYCODE": "k",
      "ROUND_START": "FALSE"
    },
    {
      "ROUND": 82,
      "MONKEY": "VILLAGE_3",
      "UPGRADE": "2-0-0",
      "UPGRADE_DIFF": "2-0-0",
      "TARGET": null,
      "TARGET_POS": null,
      "POSITION": "2078, 570",
      "KEYCODE": "k",
      "ROUND_START": "FALSE"
    },
    {
      "ROUND": 83,
      "MONKEY": "ALCH_3",
      "UPGRADE": null,
      "UPGRADE_DIFF": null,
      "TARGET": null,
      "TARGET_POS": null,
      "POSITION": "2132, 691",
      "KEYCODE": "f",
      "ROUND_START": "FALSE"
    },
    {
      "ROUND": 83,
      "MONKEY": "ALCH_3",
      "UPGRADE": "4-2-0",
      "UPGRADE_DIFF": "4-2-0",
      "TARGET": null,
      "TARGET_POS": null,
      "POSITION": "2132, 691",
      "KEYCODE": "f",
      "ROUND_START": "FALSE"
    },
    {
      "ROUND": 84,
      "MONKEY": "SPIKE_2",
      "UPGRADE": null,
      "UPGRADE_DIFF": null,
      "TARGET": null,
      "TARGET_POS": null,
      "POSITION": "2032, 785",
      "KEYCODE": "j",
      "ROUND_START": "FALSE"
    },
    {
      "ROUND": 84,
      "MONKEY": "SPIKE_2",
      "UPGRADE": "3-2-0",
      "UPGRADE_DIFF": "3-2-0",
      "TARGET": null,
      "TARGET_POS": null,
      "POSITION": "2032, 785",
      "KEYCODE": "j",
      "ROUND_START": "FALSE"
    },
    {
      "ROUND": 85,
      "MONKEY": "SNIPER_1",
      "UPGRADE": null,
      "UPGRADE_DIFF": null,
      "TARGET": "STRONG",
      "TARGET_POS": null,
      "POSITION": "1150, 207",
      "KEYCODE": "z",
      "ROUND_START": "FALSE"
    },
    {
      "ROUND": 85,
      "MONKEY": "SNIPER_1",
      "UPGRADE": "3-0-0",
      "UPGRADE_DIFF": "3-0-0",
      "TARGET": null,
      "TARGET_POS": null,
      "POSITION": "1150, 207",
      "KEYCODE": "z",
      "ROUND_START": "FALSE"
    },
    {
      "ROUND": 86,
      "MONKEY": "SNIPER_1",
      "UPGRADE": "4-0-2",
      "UPGRADE_DIFF": "1-0-2",
      "TARGET": null,
      "TARGET_POS": null,
      "POSITION": "1150, 207",
      "KEYCODE": "z",
      "ROUND_START": "FALSE"
    },
    {
      "ROUND": 88,
      "MONKEY": "BOOMERANG_1",
      "UPGRADE": null,
      "UPGRADE_DIFF": null,
      "TARGET": "STRONG",
      "TARGET_POS": null,
      "POSITION": "1083, 578",
      "KEYCODE": "w",
      "ROUND_START": "FALSE"
    },
    {
      "ROUND": 88,
      "MONKEY": "BOOMERANG_1",
      "UPGRADE": "2000-02-04",
      "UPGRADE_DIFF": "2000-02-04",
      "TARGET": null,
      "TARGET_POS": null,
      "POSITION": "1083, 578",
      "KEYCODE": "w",
      "ROUND_START": "FALSE"
    },
    {
      "ROUND": 91,
      "MONKEY": "BOOMERANG_2",
      "UPGRADE": null,
      "UPGRADE_DIFF": null,
      "TARGET": "STRONG",
      "TARGET_POS": null,
      "POSITION": "981, 562",
      "KEYCODE": "w",
      "ROUND_START": "FALSE"
    },
    {
      "ROUND": 91,
      "MONKEY": "BOOMERANG_2",
      "UPGRADE": "2000-02-04",
      "UPGRADE_DIFF": "2000-02-04",
      "TARGET": null,
      "TARGET_POS": null,
      "POSITION": "981, 562",
      "KEYCODE": "w",
      "ROUND_START": "FALSE"
    },
    {
      "ROUND": 92,
      "MONKEY": "GLUE_1",
      "UPGRADE": null,
      "UPGRADE_DIFF": null,
      "TARGET": "STRONG",
      "TARGET_POS": null,
      "POSITION": "899, 481",
      "KEYCODE": "y",
      "ROUND_START": "FALSE"
    },
    {
      "ROUND": 92,
      "MONKEY": "GLUE_1",
      "UPGRADE": "2000-01-04",
      "UPGRADE_DIFF": "2000-01-04",
      "TARGET": null,
      "TARGET_POS": null,
      "POSITION": "899, 481",
      "KEYCODE": "y",
      "ROUND_START": "FALSE"
    },
    {
      "ROUND": 93,
      "MONKEY": "BOOMERANG_3",
      "UPGRADE": null,
      "UPGRADE_DIFF": null,
      "TARGET": "STRONG",
      "TARGET_POS": null,
      "POSITION": "1257, 884",
      "KEYCODE": "w",
      "ROUND_START": "FALSE"
    },
    {
      "ROUND": 93,
      "MONKEY": "BOOMERANG_3",
      "UPGRADE": "2000-02-04",
      "UPGRADE_DIFF": "2000-02-04",
      "TARGET": null,
      "TARGET_POS": null,
      "POSITION": "1257, 884",
      "KEYCODE": "w",
      "ROUND_START": "FALSE"
    },
    {
      "ROUND": 96,
      "MONKEY": "MORTAR_1",
      "UPGRADE": null,
      "UPGRADE_DIFF": null,
      "TARGET": null,
      "TARGET_POS": "1011, 725",
      "POSITION": "959, 244",
      "KEYCODE": "n",
      "ROUND_START": "FALSE"
    },
    {
      "ROUND": 96,
      "MONKEY": "MORTAR_1",
      "UPGRADE": "0-0-4",
      "UPGRADE_DIFF": "0-0-4",
      "TARGET": null,
      "TARGET_POS": null,
      "POSITION": "959, 244",
      "KEYCODE": "n",
      "ROUND_START": "FALSE"
    }
  ]